plover_word_tray/config_ui.py
plover_word_tray/pseudo.py
plover_word_tray/resources_rc.py
plover_word_tray/sorting.py
plover_word_tray/word_tray_config.py
plover_word_tray/word_tray_macros.py
plover_word_tray/word_tray_suggestions.py
plover_word_tray/word_tray_ui.py
plover_word_tray-0.0.10.dist-info/LICENSE.txt
plover_word_tray-0.0.10.dist-info/METADATA
plover_word_tray-0.0.10.dist-info/WHEEL
plover_word_tray-0.0.10.dist-info/entry_points.txt
plover_word_tray-0.0.10.dist-info/top_level.txt
plover_word_tray-0.0.10.dist-info/zip-safe
plover_word_tray-0.0.10.dist-info/RECORD
