Metadata-Version: 2.1
Name: plover-word-tray
Version: 0.0.10
Summary: Autolookup GUI Plugin for Plover
Home-page: https://github.com/Kaoffie/plover_word_tray
Author: Kaoffie
Author-email: kaoffie@gmail.com
License: MIT License (MIT)
Keywords: plover plover_plugin
Platform: UNKNOWN
Classifier: Development Status :: 4 - Beta
Classifier: Environment :: Plugins
Classifier: Intended Audience :: End Users/Desktop
Classifier: License :: OSI Approved :: MIT License
Classifier: Operating System :: OS Independent
Classifier: Programming Language :: Python :: 3
Classifier: Programming Language :: Python :: 3.6
License-File: LICENSE.txt
Requires-Dist: plover (>=4.0.0.dev8)
